hcut.py
setup.py
hcut.egg-info/PKG-INFO
hcut.egg-info/SOURCES.txt
hcut.egg-info/dependency_links.txt
hcut.egg-info/requires.txt
hcut.egg-info/top_level.txt
scripts/hcut
test/test_hcut.py