Metadata-Version: 1.0
Name: hcut
Version: 0.1.5
Summary: Cutter for text files with header
Home-page: https://github.com/tototoshi/hcut
Author: Toshiyuki Takahashi
Author-email: t.toshi.0412 at gmail.com
License: BSD
Keywords: cut,tsv
Platform: POSIX
Platform: Windows
Classifier: License :: OSI Approved :: BSD License
Classifier: Programming Language :: Python
Classifier: Development Status :: 4 - Beta
Classifier: Environment :: Console
Classifier: Intended Audience :: Developers
Classifier: Topic :: Utilities 
Classifier: Topic :: Software Development
